xmltest/__init__.py
xmltest/instance_docs.py
xmltest/types.py
xmltest/validator.py
xmltest-0.1a3.dist-info/entry_points.txt
xmltest-0.1a3.dist-info/LICENSE
xmltest-0.1a3.dist-info/WHEEL
xmltest-0.1a3.dist-info/METADATA
xmltest-0.1a3.dist-info/RECORD
